[{"code":"002867","endPrice":29.02,"maxPrice":29.12,"percent":1.5751,"size":3022204,"beginPrice":28.62},{"code":"002867","endPrice":28.57,"maxPrice":28.79,"percent":-0.314,"size":1484496,"beginPrice":28.71},{"code":"002867","endPrice":28.66,"maxPrice":28.99,"percent":-0.9675,"size":2049430,"beginPrice":28.99},{"code":"002867","endPrice":28.94,"maxPrice":28.96,"percent":1.5439,"size":2171200,"beginPrice":28.52},{"code":"002867","endPrice":28.5,"maxPrice":28.67,"percent":0.3521,"size":1856410,"beginPrice":28.57},{"code":"002867","endPrice":28.4,"maxPrice":28.49,"percent":0.6735,"size":1275631,"beginPrice":28.26},{"code":"002867","endPrice":28.21,"maxPrice":28.4,"percent":-0.4938,"size":1378715,"beginPrice":28.4},{"code":"002867","endPrice":28.35,"maxPrice":28.45,"percent":0.2475,"size":1178030,"beginPrice":28.25},{"code":"002867","endPrice":28.28,"maxPrice":28.72,"percent":-0.9804,"size":2119910,"beginPrice":28.63},{"code":"002867","endPrice":28.56,"maxPrice":28.94,"percent":-0.1399,"size":1950115,"beginPrice":28.6},{"code":"002867","endPrice":28.6,"maxPrice":28.75,"percent":-0.7289,"size":1945998,"beginPrice":28.73},{"code":"002867","endPrice":28.81,"maxPrice":29.11,"percent":0.1739,"size":2451050,"beginPrice":28.72},{"code":"002867","endPrice":28.76,"maxPrice":28.81,"percent":0.5594,"size":1512056,"beginPrice":28.58},{"code":"002867","endPrice":28.6,"maxPrice":28.88,"percent":-0.7634,"size":2039205,"beginPrice":28.82},{"code":"002867","endPrice":28.82,"maxPrice":28.89,"percent":0.139,"size":1344547,"beginPrice":28.78},{"code":"002867","endPrice":28.78,"maxPrice":29.13,"percent":-1.3032,"size":2421346,"beginPrice":29.12},{"code":"002867","endPrice":29.16,"maxPrice":29.45,"percent":-0.137,"size":2795264,"beginPrice":29.17},{"code":"002867","endPrice":29.2,"maxPrice":29.25,"percent":0.6897,"size":1682324,"beginPrice":28.95},{"code":"002867","endPrice":29,"maxPrice":29.44,"percent":-1.5614,"size":3323362,"beginPrice":29.44},{"code":"002867","endPrice":29.46,"maxPrice":29.47,"percent":1.4463,"size":3725886,"beginPrice":29.09},{"code":"002867","endPrice":29.04,"maxPrice":29.28,"percent":0.4497,"size":2813622,"beginPrice":29.04},{"code":"002867","endPrice":28.91,"maxPrice":29.17,"percent":-0.276,"size":2643588,"beginPrice":28.93},{"code":"002867","endPrice":28.99,"maxPrice":29.29,"percent":-0.5489,"size":2559664,"beginPrice":29.2},{"code":"002867","endPrice":29.15,"maxPrice":29.43,"percent":-0.41,"size":2425249,"beginPrice":29.28},{"code":"002867","endPrice":29.27,"maxPrice":29.63,"percent":-0.5774,"size":2974316,"beginPrice":29.48},{"code":"002867","endPrice":29.44,"maxPrice":29.66,"percent":-0.034,"size":3574774,"beginPrice":29.65},{"code":"002867","endPrice":29.45,"maxPrice":29.65,"percent":1.5517,"size":4619265,"beginPrice":29.01},{"code":"002867","endPrice":29,"maxPrice":29.59,"percent":-1.6616,"size":4369571,"beginPrice":29.59},{"code":"002867","endPrice":29.49,"maxPrice":29.78,"percent":0.9932,"size":7114956,"beginPrice":29.36},{"code":"002867","endPrice":29.2,"maxPrice":29.64,"percent":3.2167,"size":6978305,"beginPrice":28.42},{"code":"002867","endPrice":28.29,"maxPrice":28.34,"percent":1.3978,"size":2700494,"beginPrice":27.92},{"code":"002867","endPrice":27.9,"maxPrice":28.29,"percent":-1.204,"size":2566441,"beginPrice":28.18},{"code":"002867","endPrice":28.24,"maxPrice":28.56,"percent":-0.9123,"size":2205775,"beginPrice":28.55},{"code":"002867","endPrice":28.5,"maxPrice":28.66,"percent":0.6356,"size":3049653,"beginPrice":28.33},{"code":"002867","endPrice":28.32,"maxPrice":28.4,"percent":0.7829,"size":2100770,"beginPrice":28.24},{"code":"002867","endPrice":28.1,"maxPrice":28.43,"percent":-1.126,"size":2251638,"beginPrice":28.27},{"code":"002867","endPrice":28.42,"maxPrice":28.43,"percent":0.495,"size":2895714,"beginPrice":28.34},{"code":"002867","endPrice":28.28,"maxPrice":28.33,"percent":0.569,"size":3161067,"beginPrice":28.08},{"code":"002867","endPrice":28.12,"maxPrice":28.17,"percent":-0.2129,"size":2532503,"beginPrice":28.17},{"code":"002867","endPrice":28.18,"maxPrice":28.2,"percent":0.5351,"size":3141129,"beginPrice":27.82},{"code":"002867","endPrice":28.03,"maxPrice":28.66,"percent":1.301,"size":5754629,"beginPrice":27.66},{"code":"002867","endPrice":27.67,"maxPrice":27.96,"percent":0.1448,"size":2364140,"beginPrice":27.71},{"code":"002867","endPrice":27.63,"maxPrice":27.73,"percent":0,"size":1786894,"beginPrice":27.59},{"code":"002867","endPrice":27.63,"maxPrice":27.74,"percent":-0.3965,"size":1753718,"beginPrice":27.74},{"code":"002867","endPrice":27.74,"maxPrice":27.76,"percent":0.5437,"size":1726267,"beginPrice":27.51},{"code":"002867","endPrice":27.59,"maxPrice":27.8,"percent":0.0725,"size":2061144,"beginPrice":27.67},{"code":"002867","endPrice":27.57,"maxPrice":27.86,"percent":0.1817,"size":1801032,"beginPrice":27.54},{"code":"002867","endPrice":27.52,"maxPrice":28.18,"percent":-2.1685,"size":2624734,"beginPrice":28.02},{"code":"002867","endPrice":28.13,"maxPrice":28.2,"percent":0.68,"size":3021259,"beginPrice":27.87},{"code":"002867","endPrice":27.94,"maxPrice":28.15,"percent":0.3953,"size":1758085,"beginPrice":27.81},{"code":"002867","endPrice":27.83,"maxPrice":28.1,"percent":-1.0313,"size":1832465,"beginPrice":28.1},{"code":"002867","endPrice":28.12,"maxPrice":28.15,"percent":2.7402,"size":3911300,"beginPrice":27.39},{"code":"002867","endPrice":27.37,"maxPrice":27.76,"percent":-0.9768,"size":2091402,"beginPrice":27.59},{"code":"002867","endPrice":27.64,"maxPrice":27.85,"percent":-0.7897,"size":1769136,"beginPrice":27.78},{"code":"002867","endPrice":27.86,"maxPrice":27.96,"percent":0.0359,"size":2791232,"beginPrice":27.7},{"code":"002867","endPrice":27.85,"maxPrice":28.26,"percent":-1.2411,"size":3033749,"beginPrice":28.2},{"code":"002867","endPrice":28.2,"maxPrice":28.7,"percent":-0.9136,"size":2941785,"beginPrice":28.36},{"code":"002867","endPrice":28.46,"maxPrice":28.5,"percent":0.2113,"size":2844909,"beginPrice":28.38},{"code":"002867","endPrice":29,"maxPrice":29.09,"percent":1.6118,"size":2532262,"beginPrice":28.54},{"code":"002867","endPrice":28.54,"maxPrice":30.64,"percent":-7.0964,"size":4246898,"beginPrice":30.51},{"code":"002867","endPrice":30.72,"maxPrice":30.95,"percent":-0.2921,"size":1588381,"beginPrice":30.74},{"code":"002867","endPrice":30.81,"maxPrice":30.93,"percent":-0.388,"size":1787986,"beginPrice":30.92},{"code":"002867","endPrice":30.93,"maxPrice":30.97,"percent":1.911,"size":2876612,"beginPrice":30.66},{"code":"002867","endPrice":30.35,"maxPrice":30.96,"percent":-0.9465,"size":2735660,"beginPrice":30.58},{"code":"002867","endPrice":30.64,"maxPrice":31.55,"percent":-3.6781,"size":5357431,"beginPrice":31.54},{"code":"002867","endPrice":31.81,"maxPrice":31.97,"percent":1.9225,"size":5776641,"beginPrice":31.21},{"code":"002867","endPrice":31.21,"maxPrice":31.58,"percent":-0.6367,"size":3913805,"beginPrice":31.52},{"code":"002867","endPrice":31.41,"maxPrice":31.47,"percent":0.6731,"size":4076372,"beginPrice":31.21},{"code":"002867","endPrice":31.2,"maxPrice":31.42,"percent":0.7101,"size":3839499,"beginPrice":30.97},{"code":"002867","endPrice":30.98,"maxPrice":31.05,"percent":0.3238,"size":2585505,"beginPrice":30.88},{"code":"002867","endPrice":30.88,"maxPrice":30.95,"percent":1.1796,"size":3647188,"beginPrice":30.38},{"code":"002867","endPrice":30.52,"maxPrice":30.65,"percent":0.8592,"size":2014062,"beginPrice":30.3},{"code":"002867","endPrice":30.26,"maxPrice":30.58,"percent":-1.3046,"size":2201993,"beginPrice":30.51},{"code":"002867","endPrice":30.66,"maxPrice":30.96,"percent":-0.2602,"size":2624952,"beginPrice":30.62},{"code":"002867","endPrice":30.74,"maxPrice":30.79,"percent":1.0852,"size":2568209,"beginPrice":30.25},{"code":"002867","endPrice":30.41,"maxPrice":30.85,"percent":-1.1378,"size":3602431,"beginPrice":30.6},{"code":"002867","endPrice":30.76,"maxPrice":31.46,"percent":-2.0694,"size":3152739,"beginPrice":31.37},{"code":"002867","endPrice":31.41,"maxPrice":31.73,"percent":-0.5383,"size":2831877,"beginPrice":31.6},{"code":"002867","endPrice":31.58,"maxPrice":31.96,"percent":0.7015,"size":4561584,"beginPrice":31.37},{"code":"002867","endPrice":31.36,"maxPrice":31.4,"percent":0.7712,"size":2398044,"beginPrice":31.1},{"code":"002867","endPrice":31.12,"maxPrice":31.48,"percent":-1.2063,"size":3501446,"beginPrice":31.36},{"code":"002867","endPrice":31.5,"maxPrice":31.78,"percent":1.5147,"size":5421228,"beginPrice":30.83},{"code":"002867","endPrice":31.03,"maxPrice":31.27,"percent":0.3233,"size":3687355,"beginPrice":30.81},{"code":"002867","endPrice":30.93,"maxPrice":31.12,"percent":1.9782,"size":3347001,"beginPrice":30.3},{"code":"002867","endPrice":30.33,"maxPrice":31.14,"percent":-3.7448,"size":4155735,"beginPrice":31.14},{"code":"002867","endPrice":31.51,"maxPrice":31.78,"percent":-0.5366,"size":3009603,"beginPrice":31.53},{"code":"002867","endPrice":31.68,"maxPrice":32.42,"percent":-1.8283,"size":5586741,"beginPrice":32.26},{"code":"002867","endPrice":32.27,"maxPrice":32.37,"percent":2.9346,"size":6100428,"beginPrice":31.49},{"code":"002867","endPrice":31.35,"maxPrice":31.57,"percent":0.2238,"size":3014281,"beginPrice":31.3},{"code":"002867","endPrice":31.28,"maxPrice":31.94,"percent":0.3529,"size":4195969,"beginPrice":31.7},{"code":"002867","endPrice":31.17,"maxPrice":31.46,"percent":2.2638,"size":4770287,"beginPrice":30.28},{"code":"002867","endPrice":30.48,"maxPrice":32.41,"percent":-7.4119,"size":7767464,"beginPrice":32.41},{"code":"002867","endPrice":32.92,"maxPrice":34.67,"percent":-1.1114,"size":7206061,"beginPrice":34.6},{"code":"002867","endPrice":33.29,"maxPrice":33.79,"percent":1.6489,"size":7307541,"beginPrice":32.88},{"code":"002867","endPrice":32.75,"maxPrice":33.19,"percent":-0.0915,"size":6212006,"beginPrice":32.69},{"code":"002867","endPrice":32.78,"maxPrice":32.95,"percent":1.1104,"size":5648285,"beginPrice":32.25},{"code":"002867","endPrice":32.42,"maxPrice":33.86,"percent":-3.2816,"size":7022453,"beginPrice":33.53},{"code":"002867","endPrice":33.52,"maxPrice":35.63,"percent":-6.1853,"size":8853129,"beginPrice":35.63},{"code":"002867","endPrice":35.73,"maxPrice":36.6,"percent":-3.013,"size":8218865,"beginPrice":36.38},{"code":"002867","endPrice":36.84,"maxPrice":39.49,"percent":-4.3862,"size":10689311,"beginPrice":38.53},{"code":"002867","endPrice":38.53,"maxPrice":39.7,"percent":-1.2811,"size":10632044,"beginPrice":39.04},{"code":"002867","endPrice":39.03,"maxPrice":39.34,"percent":-0.4844,"size":12006587,"beginPrice":38.33},{"code":"002867","endPrice":39.22,"maxPrice":40.56,"percent":6.1434,"size":16797534,"beginPrice":36.82},{"code":"002867","endPrice":36.95,"maxPrice":37.77,"percent":-0.7521,"size":9546888,"beginPrice":37.23},{"code":"002867","endPrice":37.23,"maxPrice":37.7,"percent":-1.1155,"size":11125573,"beginPrice":37.7},{"code":"002867","endPrice":37.65,"maxPrice":40.65,"percent":-6.1097,"size":15288403,"beginPrice":39.81},{"code":"002867","endPrice":40.1,"maxPrice":41.6,"percent":-0.1494,"size":14368108,"beginPrice":39},{"code":"002867","endPrice":40.16,"maxPrice":43,"percent":-9.9753,"size":19788638,"beginPrice":43},{"code":"002867","endPrice":44.61,"maxPrice":46.09,"percent":6.2143,"size":32280436,"beginPrice":46.09},{"code":"002867","endPrice":42,"maxPrice":42,"percent":10.0052,"size":109512,"beginPrice":42},{"code":"002867","endPrice":38.18,"maxPrice":38.18,"percent":9.9971,"size":17921,"beginPrice":38.18},{"code":"002867","endPrice":34.71,"maxPrice":34.71,"percent":10.0158,"size":15440,"beginPrice":34.71},{"code":"002867","endPrice":31.55,"maxPrice":31.55,"percent":10.007,"size":9899,"beginPrice":31.55},{"code":"002867","endPrice":28.68,"maxPrice":28.68,"percent":43.9759,"size":25230,"beginPrice":23.9}]