[{"date":"2017-12-11","code":"sz300622","begin":27.3,"high":27.59,"low":27.18,"end":27.26,"percent":-0.001465,"size":625675},{"date":"2017-12-08","code":"sz300622","begin":26.72,"high":27.69,"low":26.72,"end":27.3,"percent":0.01487,"size":547900},{"date":"2017-12-07","code":"sz300622","begin":26.83,"high":27.27,"low":26.83,"end":26.9,"percent":-0.00628,"size":310640},{"date":"2017-12-06","code":"sz300622","begin":26.23,"high":27.1,"low":26.23,"end":27.07,"percent":0.028886,"size":544485},{"date":"2017-12-05","code":"sz300622","begin":28,"high":28.58,"low":26,"end":26.31,"percent":-0.064034,"size":1287763},{"date":"2017-12-04","code":"sz300622","begin":28.5,"high":28.8,"low":27.65,"end":28.11,"percent":-0.01782,"size":1126169},{"date":"2017-12-01","code":"sz300622","begin":27.9,"high":28.83,"low":27.75,"end":28.62,"percent":0.025072,"size":1222895},{"date":"2017-11-30","code":"sz300622","begin":27.85,"high":28,"low":27.65,"end":27.92,"percent":0.006852,"size":994100},{"date":"2017-11-29","code":"sz300622","begin":27.4,"high":27.77,"low":26.95,"end":27.73,"percent":0.00873,"size":895595},{"date":"2017-11-28","code":"sz300622","begin":26.74,"high":27.68,"low":26.69,"end":27.49,"percent":0.027664,"size":956485},{"date":"2017-11-27","code":"sz300622","begin":26.6,"high":27.16,"low":26.5,"end":26.75,"percent":0.005639,"size":730700},{"date":"2017-11-24","code":"sz300622","begin":26.48,"high":26.98,"low":26.39,"end":26.6,"percent":-0.003745,"size":702885},{"date":"2017-11-23","code":"sz300622","begin":27.98,"high":27.99,"low":26.67,"end":26.7,"percent":-0.048128,"size":1723969},{"date":"2017-11-22","code":"sz300622","begin":28.55,"high":28.67,"low":27.82,"end":28.05,"percent":-0.015444,"size":1562249},{"date":"2017-11-21","code":"sz300622","begin":30.22,"high":30.25,"low":27.62,"end":28.49,"percent":-0.035871,"size":2534944},{"date":"2017-11-20","code":"sz300622","begin":29.11,"high":30.87,"low":29.1,"end":29.55,"percent":0.038664,"size":1813245},{"date":"2017-11-17","code":"sz300622","begin":30.9,"high":31.18,"low":28.15,"end":28.45,"percent":-0.090473,"size":2754663},{"date":"2017-11-16","code":"sz300622","begin":32.03,"high":32.59,"low":31.25,"end":31.28,"percent":-0.028571,"size":1594469},{"date":"2017-11-15","code":"sz300622","begin":32.94,"high":32.94,"low":31.87,"end":32.2,"percent":-0.023651,"size":1857990},{"date":"2017-11-14","code":"sz300622","begin":32.3,"high":32.99,"low":31.86,"end":32.98,"percent":0.018215,"size":2679085},{"date":"2017-11-13","code":"sz300622","begin":31.7,"high":32.4,"low":31.41,"end":32.39,"percent":0.022734,"size":1889490},{"date":"2017-11-10","code":"sz300622","begin":31.18,"high":32.11,"low":31.1,"end":31.67,"percent":0.012468,"size":1762624},{"date":"2017-11-09","code":"sz300622","begin":30.88,"high":31.3,"low":30.7,"end":31.28,"percent":0.009684,"size":985261},{"date":"2017-11-08","code":"sz300622","begin":30.7,"high":31.4,"low":30.62,"end":30.98,"percent":0.006171,"size":1484635},{"date":"2017-11-07","code":"sz300622","begin":30.6,"high":30.79,"low":30.01,"end":30.79,"percent":0.006209,"size":1447161},{"date":"2017-11-06","code":"sz300622","begin":30.46,"high":30.87,"low":30.11,"end":30.6,"percent":0.017287,"size":1185208},{"date":"2017-11-03","code":"sz300622","begin":31,"high":31.3,"low":29.88,"end":30.08,"percent":-0.035897,"size":1719645},{"date":"2017-11-02","code":"sz300622","begin":32.23,"high":32.23,"low":31.19,"end":31.2,"percent":-0.031958,"size":1534070},{"date":"2017-11-01","code":"sz300622","begin":31.92,"high":32.75,"low":31.73,"end":32.23,"percent":0.000932,"size":1846955},{"date":"2017-10-31","code":"sz300622","begin":31.38,"high":32.39,"low":31.38,"end":32.2,"percent":0.027441,"size":1615057},{"date":"2017-10-30","code":"sz300622","begin":32.65,"high":33.22,"low":31.03,"end":31.34,"percent":-0.050878,"size":2355862},{"date":"2017-10-27","code":"sz300622","begin":33.1,"high":33.47,"low":32.55,"end":33.02,"percent":-0.014328,"size":3109792},{"date":"2017-10-26","code":"sz300622","begin":31.5,"high":33.5,"low":31.21,"end":33.5,"percent":0.060127,"size":4439975},{"date":"2017-10-25","code":"sz300622","begin":31,"high":31.75,"low":30.88,"end":31.6,"percent":0.012496,"size":2148958},{"date":"2017-10-24","code":"sz300622","begin":32,"high":32.02,"low":30.6,"end":31.21,"percent":-0.032248,"size":2729478},{"date":"2017-10-23","code":"sz300622","begin":31.83,"high":32.37,"low":31.6,"end":32.25,"percent":0.007812,"size":2329215},{"date":"2017-10-20","code":"sz300622","begin":32.78,"high":32.84,"low":31.25,"end":32,"percent":-0.021706,"size":3082630},{"date":"2017-10-19","code":"sz300622","begin":32.9,"high":33.43,"low":32.25,"end":32.71,"percent":-0.025908,"size":4063541},{"date":"2017-10-18","code":"sz300622","begin":31.96,"high":33.98,"low":31.58,"end":33.58,"percent":0.018811,"size":7114715},{"date":"2017-10-17","code":"sz300622","begin":30.52,"high":33.66,"low":30.52,"end":32.96,"percent":0.077124,"size":7516965},{"date":"2017-10-16","code":"sz300622","begin":32.72,"high":32.72,"low":30.5,"end":30.6,"percent":-0.039548,"size":4207459},{"date":"2017-10-13","code":"sz300622","begin":29.17,"high":31.86,"low":29.01,"end":31.86,"percent":0.100138,"size":3058945},{"date":"2017-10-12","code":"sz300622","begin":29.32,"high":29.68,"low":28.62,"end":28.96,"percent":-0.016638,"size":965723},{"date":"2017-10-11","code":"sz300622","begin":29.94,"high":29.99,"low":29.4,"end":29.45,"percent":-0.016366,"size":950845},{"date":"2017-10-10","code":"sz300622","begin":29.31,"high":29.98,"low":29.22,"end":29.94,"percent":0.02359,"size":1141080},{"date":"2017-10-09","code":"sz300622","begin":29.67,"high":29.92,"low":29.12,"end":29.25,"percent":-0.001366,"size":937778},{"date":"2017-09-29","code":"sz300622","begin":28.99,"high":29.5,"low":28.85,"end":29.29,"percent":0.01,"size":1083453},{"date":"2017-09-28","code":"sz300622","begin":28.59,"high":29.45,"low":28.5,"end":29,"percent":0.010453,"size":1211337},{"date":"2017-09-27","code":"sz300622","begin":28.3,"high":28.79,"low":28.1,"end":28.7,"percent":-0.002433,"size":732882},{"date":"2017-09-26","code":"sz300622","begin":28.59,"high":28.77,"low":27.58,"end":28.77,"percent":0.000696,"size":1213228},{"date":"2017-09-25","code":"sz300622","begin":28.63,"high":29.25,"low":28.63,"end":28.75,"percent":-0.002775,"size":1013851},{"date":"2017-09-22","code":"sz300622","begin":28.59,"high":28.96,"low":28.17,"end":28.83,"percent":0.002783,"size":1037978},{"date":"2017-09-21","code":"sz300622","begin":29.16,"high":29.55,"low":28.64,"end":28.75,"percent":-0.01406,"size":1443000},{"date":"2017-09-20","code":"sz300622","begin":29.36,"high":29.36,"low":28.6,"end":29.16,"percent":0.01958,"size":904830},{"date":"2017-09-19","code":"sz300622","begin":28.58,"high":29.18,"low":28.41,"end":28.6,"percent":-0.001745,"size":642755},{"date":"2017-09-18","code":"sz300622","begin":28.58,"high":28.69,"low":27.95,"end":28.65,"percent":0.004558,"size":808185},{"date":"2017-09-15","code":"sz300622","begin":29.17,"high":29.28,"low":28.5,"end":28.52,"percent":-0.021277,"size":587200},{"date":"2017-09-14","code":"sz300622","begin":29.31,"high":29.47,"low":29.01,"end":29.14,"percent":-0.0058,"size":488365},{"date":"2017-09-13","code":"sz300622","begin":28.98,"high":29.36,"low":28.86,"end":29.31,"percent":0.013836,"size":522492},{"date":"2017-09-12","code":"sz300622","begin":29.81,"high":29.93,"low":28.81,"end":28.91,"percent":-0.029214,"size":982929},{"date":"2017-09-11","code":"sz300622","begin":29.21,"high":29.78,"low":29.21,"end":29.78,"percent":0.016035,"size":784386},{"date":"2017-09-08","code":"sz300622","begin":29.35,"high":29.78,"low":28.91,"end":29.31,"percent":-0.012133,"size":902099},{"date":"2017-09-07","code":"sz300622","begin":29.56,"high":30.18,"low":29.2,"end":29.67,"percent":0.001688,"size":1103637},{"date":"2017-09-06","code":"sz300622","begin":29.9,"high":29.9,"low":29.05,"end":29.62,"percent":-0.012337,"size":1337695},{"date":"2017-09-05","code":"sz300622","begin":30.2,"high":30.8,"low":29.8,"end":29.99,"percent":-0.006954,"size":1324206},{"date":"2017-09-04","code":"sz300622","begin":29.87,"high":30.78,"low":29.56,"end":30.2,"percent":0.007338,"size":2078202},{"date":"2017-09-01","code":"sz300622","begin":29.9,"high":29.99,"low":29.39,"end":29.98,"percent":0.003347,"size":1553831},{"date":"2017-08-31","code":"sz300622","begin":29,"high":29.93,"low":28.7,"end":29.88,"percent":0.038221,"size":1738511},{"date":"2017-08-30","code":"sz300622","begin":28.92,"high":29.42,"low":28.72,"end":28.78,"percent":-0.009294,"size":1602300},{"date":"2017-08-29","code":"sz300622","begin":29,"high":29.96,"low":28.7,"end":29.05,"percent":-0.005478,"size":2478468},{"date":"2017-08-28","code":"sz300622","begin":28.07,"high":29.44,"low":27.94,"end":29.21,"percent":0.040613,"size":2494861},{"date":"2017-08-25","code":"sz300622","begin":27.2,"high":28.28,"low":27.1,"end":28.07,"percent":0.029714,"size":1515739},{"date":"2017-08-24","code":"sz300622","begin":27.49,"high":27.98,"low":27.1,"end":27.26,"percent":-0.008367,"size":1079770},{"date":"2017-08-23","code":"sz300622","begin":27.36,"high":27.65,"low":27.01,"end":27.49,"percent":0.004384,"size":1124409},{"date":"2017-08-22","code":"sz300622","begin":27.65,"high":27.71,"low":27.12,"end":27.37,"percent":-0.006534,"size":746377},{"date":"2017-08-21","code":"sz300622","begin":26.96,"high":27.7,"low":26.93,"end":27.55,"percent":0.021127,"size":739282},{"date":"2017-08-18","code":"sz300622","begin":27.26,"high":27.26,"low":26.82,"end":26.98,"percent":-0.014609,"size":466900},{"date":"2017-08-17","code":"sz300622","begin":27.38,"high":27.46,"low":27.02,"end":27.38,"percent":-0.00073,"size":633260},{"date":"2017-08-16","code":"sz300622","begin":27.04,"high":27.56,"low":26.96,"end":27.4,"percent":0.013314,"size":1262750},{"date":"2017-08-15","code":"sz300622","begin":26.91,"high":27.1,"low":26.7,"end":27.04,"percent":0.012734,"size":548785},{"date":"2017-08-14","code":"sz300622","begin":26.07,"high":26.8,"low":26.07,"end":26.7,"percent":0.024166,"size":371300},{"date":"2017-08-11","code":"sz300622","begin":26.59,"high":26.73,"low":25.91,"end":26.07,"percent":-0.027239,"size":324595},{"date":"2017-08-10","code":"sz300622","begin":26.83,"high":27.05,"low":26.73,"end":26.8,"percent":-0.003347,"size":426600},{"date":"2017-08-09","code":"sz300622","begin":26.81,"high":27.02,"low":26.74,"end":26.89,"percent":0.00149,"size":302500},{"date":"2017-08-08","code":"sz300622","begin":26.84,"high":27.06,"low":26.55,"end":26.85,"percent":-0.001488,"size":514086},{"date":"2017-08-07","code":"sz300622","begin":26.81,"high":27.14,"low":26.75,"end":26.89,"percent":0.002984,"size":288280},{"date":"2017-08-04","code":"sz300622","begin":27.19,"high":27.19,"low":26.75,"end":26.81,"percent":-0.011066,"size":445715},{"date":"2017-08-03","code":"sz300622","begin":26.9,"high":27.45,"low":26.58,"end":27.11,"percent":0.008932,"size":604634},{"date":"2017-08-02","code":"sz300622","begin":27.15,"high":27.48,"low":26.85,"end":26.87,"percent":-0.010313,"size":662885},{"date":"2017-08-01","code":"sz300622","begin":26.8,"high":27.22,"low":26.8,"end":27.15,"percent":0.011927,"size":598962},{"date":"2017-07-31","code":"sz300622","begin":26.78,"high":26.98,"low":26.53,"end":26.83,"percent":0.002991,"size":602962},{"date":"2017-07-28","code":"sz300622","begin":27.41,"high":27.56,"low":26.73,"end":26.75,"percent":-0.01582,"size":1001045},{"date":"2017-07-27","code":"sz300622","begin":25.92,"high":27.18,"low":25.7,"end":27.18,"percent":0.050232,"size":1192182},{"date":"2017-07-26","code":"sz300622","begin":26.5,"high":26.5,"low":25.81,"end":25.88,"percent":-0.010325,"size":316075},{"date":"2017-07-25","code":"sz300622","begin":26.08,"high":26.52,"low":26.08,"end":26.15,"percent":-0.005325,"size":491200},{"date":"2017-07-24","code":"sz300622","begin":25.43,"high":26.49,"low":25.43,"end":26.29,"percent":0.00728,"size":759460},{"date":"2017-07-21","code":"sz300622","begin":26.35,"high":26.73,"low":25.88,"end":26.1,"percent":-0.017319,"size":698835},{"date":"2017-07-20","code":"sz300622","begin":27,"high":27.27,"low":26.52,"end":26.56,"percent":-0.009325,"size":800995},{"date":"2017-07-19","code":"sz300622","begin":26.52,"high":26.98,"low":26.31,"end":26.81,"percent":0.006004,"size":681607},{"date":"2017-07-18","code":"sz300622","begin":26.39,"high":27,"low":26.2,"end":26.65,"percent":0.000375,"size":854672},{"date":"2017-07-17","code":"sz300622","begin":29.02,"high":29.18,"low":26.64,"end":26.64,"percent":-0.1,"size":1831501},{"date":"2017-07-14","code":"sz300622","begin":29.83,"high":30.25,"low":29.42,"end":29.6,"percent":-0.007378,"size":563474},{"date":"2017-07-13","code":"sz300622","begin":30.3,"high":30.3,"low":29.72,"end":29.82,"percent":-0.020368,"size":958280},{"date":"2017-07-12","code":"sz300622","begin":29.96,"high":30.47,"low":29.36,"end":30.44,"percent":0.01704,"size":1131095},{"date":"2017-07-11","code":"sz300622","begin":30.45,"high":30.64,"low":29.73,"end":29.93,"percent":-0.020615,"size":1518000},{"date":"2017-07-10","code":"sz300622","begin":31.99,"high":32,"low":30.38,"end":30.56,"percent":-0.049456,"size":2844100},{"date":"2017-07-07","code":"sz300622","begin":31.35,"high":32.84,"low":31.31,"end":32.15,"percent":0.023234,"size":3099812},{"date":"2017-07-06","code":"sz300622","begin":31.42,"high":31.48,"low":30.9,"end":31.42,"percent":0.004797,"size":1750261},{"date":"2017-07-05","code":"sz300622","begin":30.46,"high":31.27,"low":30.46,"end":31.27,"percent":0.021895,"size":1443347},{"date":"2017-07-04","code":"sz300622","begin":30.68,"high":30.88,"low":30.48,"end":30.6,"percent":-0.002608,"size":942305},{"date":"2017-07-03","code":"sz300622","begin":30.49,"high":30.7,"low":30.14,"end":30.68,"percent":0.008216,"size":1190007},{"date":"2017-06-30","code":"sz300622","begin":30.01,"high":30.6,"low":29.68,"end":30.43,"percent":0.010292,"size":1217069},{"date":"2017-06-29","code":"sz300622","begin":29.58,"high":30.34,"low":29.58,"end":30.12,"percent":0.009045,"size":879969},{"date":"2017-06-28","code":"sz300622","begin":29.73,"high":30.15,"low":29.63,"end":29.85,"percent":0.001678,"size":804107},{"date":"2017-06-27","code":"sz300622","begin":29.66,"high":30.19,"low":29.6,"end":29.8,"percent":0.002017,"size":603060},{"date":"2017-06-26","code":"sz300622","begin":29.48,"high":29.82,"low":29.24,"end":29.74,"percent":0.005069,"size":573432},{"date":"2017-06-23","code":"sz300622","begin":29.5,"high":29.87,"low":28.91,"end":29.59,"percent":-0.001687,"size":930000},{"date":"2017-06-22","code":"sz300622","begin":30.52,"high":30.55,"low":29.64,"end":29.64,"percent":-0.028515,"size":899218},{"date":"2017-06-21","code":"sz300622","begin":30.55,"high":30.75,"low":30.08,"end":30.51,"percent":-0.003267,"size":742600},{"date":"2017-06-20","code":"sz300622","begin":31.09,"high":31.15,"low":30.6,"end":30.61,"percent":-0.013535,"size":1400066},{"date":"2017-06-19","code":"sz300622","begin":30.91,"high":31.2,"low":30.66,"end":31.03,"percent":0.007468,"size":687326},{"date":"2017-06-16","code":"sz300622","begin":30.99,"high":31.14,"low":30.6,"end":30.8,"percent":-0.010283,"size":980224},{"date":"2017-06-15","code":"sz300622","begin":30.31,"high":31.32,"low":30.31,"end":31.12,"percent":0.026385,"size":1268526},{"date":"2017-06-14","code":"sz300622","begin":30.49,"high":30.55,"low":29.98,"end":30.32,"percent":-0.005576,"size":671891},{"date":"2017-06-13","code":"sz300622","begin":29.5,"high":30.66,"low":29.46,"end":30.49,"percent":0.024874,"size":988490},{"date":"2017-06-12","code":"sz300622","begin":30.77,"high":30.77,"low":29.66,"end":29.75,"percent":-0.045863,"size":1151648},{"date":"2017-06-09","code":"sz300622","begin":31.2,"high":31.3,"low":30.72,"end":31.18,"percent":0.004834,"size":719264},{"date":"2017-06-08","code":"sz300622","begin":31.36,"high":31.59,"low":30.81,"end":31.03,"percent":-0.010207,"size":965700},{"date":"2017-06-07","code":"sz300622","begin":30.48,"high":31.5,"low":30.3,"end":31.35,"percent":0.034995,"size":1662794},{"date":"2017-06-06","code":"sz300622","begin":30.11,"high":30.6,"low":30.11,"end":30.49,"percent":-0.001637,"size":750846},{"date":"2017-06-05","code":"sz300622","begin":30.55,"high":31.26,"low":30.43,"end":30.54,"percent":0.007588,"size":1048848},{"date":"2017-06-02","code":"sz300622","begin":28.99,"high":30.6,"low":28.81,"end":30.31,"percent":0.032005,"size":1115121},{"date":"2017-06-01","code":"sz300622","begin":30.96,"high":31.43,"low":29.35,"end":29.37,"percent":-0.070275,"size":1613900},{"date":"2017-05-31","code":"sz300622","begin":33.01,"high":33.26,"low":31.5,"end":31.59,"percent":-0.005039,"size":2252689},{"date":"2017-05-26","code":"sz300622","begin":31.79,"high":32.27,"low":31,"end":31.75,"percent":-0.018547,"size":2026124},{"date":"2017-05-25","code":"sz300622","begin":31.7,"high":32.62,"low":30.88,"end":32.35,"percent":0.025682,"size":2737342},{"date":"2017-05-24","code":"sz300622","begin":30.03,"high":31.54,"low":29.88,"end":31.54,"percent":0.0423,"size":1527739},{"date":"2017-05-23","code":"sz300622","begin":31.15,"high":31.95,"low":30.08,"end":30.26,"percent":-0.038449,"size":1434241},{"date":"2017-05-22","code":"sz300622","begin":34.26,"high":34.26,"low":31.11,"end":31.47,"percent":-0.080094,"size":1687894},{"date":"2017-05-19","code":"sz300622","begin":34.97,"high":35.37,"low":34.11,"end":34.21,"percent":-0.022571,"size":974759},{"date":"2017-05-18","code":"sz300622","begin":35.52,"high":36.1,"low":35,"end":35,"percent":-0.023438,"size":1382650},{"date":"2017-05-17","code":"sz300622","begin":35.41,"high":36.19,"low":35.37,"end":35.84,"percent":0.005612,"size":1708172},{"date":"2017-05-16","code":"sz300622","begin":34.08,"high":35.65,"low":33.9,"end":35.64,"percent":0.034543,"size":1564996},{"date":"2017-05-15","code":"sz300622","begin":34.8,"high":35.25,"low":34.3,"end":34.45,"percent":-0.003471,"size":1405444},{"date":"2017-05-12","code":"sz300622","begin":34.39,"high":34.83,"low":33.6,"end":34.57,"percent":0.000289,"size":1847470},{"date":"2017-05-11","code":"sz300622","begin":33.85,"high":34.6,"low":33.12,"end":34.56,"percent":0.010526,"size":1607373},{"date":"2017-05-10","code":"sz300622","begin":35.21,"high":35.73,"low":34,"end":34.2,"percent":-0.030887,"size":1253907},{"date":"2017-05-09","code":"sz300622","begin":34.5,"high":35.64,"low":34.42,"end":35.29,"percent":0.018764,"size":1091691},{"date":"2017-05-08","code":"sz300622","begin":35.5,"high":35.5,"low":34.45,"end":34.64,"percent":-0.025872,"size":1072737},{"date":"2017-05-05","code":"sz300622","begin":35.78,"high":36.55,"low":35.56,"end":35.56,"percent":-0.006704,"size":1292580},{"date":"2017-05-04","code":"sz300622","begin":37.12,"high":37.18,"low":35,"end":35.8,"percent":-0.042781,"size":1567353},{"date":"2017-05-03","code":"sz300622","begin":37.06,"high":37.5,"low":36.25,"end":37.4,"percent":0.01465,"size":1934017},{"date":"2017-05-02","code":"sz300622","begin":37.1,"high":37.85,"low":36.8,"end":36.86,"percent":-0.016017,"size":1337210},{"date":"2017-04-28","code":"sz300622","begin":37.5,"high":37.78,"low":37.18,"end":37.46,"percent":-0.001067,"size":1847925},{"date":"2017-04-27","code":"sz300622","begin":35.43,"high":38,"low":34.65,"end":37.5,"percent":0.058126,"size":2945822},{"date":"2017-04-26","code":"sz300622","begin":34.86,"high":35.88,"low":34.83,"end":35.44,"percent":0.018391,"size":1651600},{"date":"2017-04-25","code":"sz300622","begin":34.8,"high":35.57,"low":34.75,"end":34.8,"percent":0.000575,"size":1234236},{"date":"2017-04-24","code":"sz300622","begin":35.88,"high":36.32,"low":34.3,"end":34.78,"percent":-0.044505,"size":1284433},{"date":"2017-04-21","code":"sz300622","begin":36.98,"high":37.27,"low":36.32,"end":36.4,"percent":-0.016216,"size":1165569},{"date":"2017-04-20","code":"sz300622","begin":38.3,"high":38.33,"low":36.3,"end":37,"percent":-0.038711,"size":2180344},{"date":"2017-04-19","code":"sz300622","begin":37.3,"high":38.99,"low":37.08,"end":38.49,"percent":0.035234,"size":2101974},{"date":"2017-04-18","code":"sz300622","begin":37.95,"high":38.39,"low":37.05,"end":37.18,"percent":-0.014577,"size":1584497},{"date":"2017-04-17","code":"sz300622","begin":38.55,"high":38.8,"low":36.22,"end":37.73,"percent":-0.057692,"size":3951436},{"date":"2017-04-14","code":"sz300622","begin":40.59,"high":41,"low":39.88,"end":40.04,"percent":-0.027683,"size":3068789},{"date":"2017-04-13","code":"sz300622","begin":41.26,"high":42.79,"low":41.04,"end":41.18,"percent":-0.012233,"size":2914425},{"date":"2017-04-12","code":"sz300622","begin":42.34,"high":43.78,"low":41.52,"end":41.69,"percent":-0.033387,"size":4464808},{"date":"2017-04-11","code":"sz300622","begin":40.46,"high":43.56,"low":40.46,"end":43.13,"percent":0.053236,"size":5950039},{"date":"2017-04-10","code":"sz300622","begin":44.4,"high":44.95,"low":40.86,"end":40.95,"percent":-0.098018,"size":7061724},{"date":"2017-04-07","code":"sz300622","begin":48,"high":48.38,"low":44.8,"end":45.4,"percent":-0.069672,"size":8412143},{"date":"2017-04-06","code":"sz300622","begin":45.02,"high":49.8,"low":44.5,"end":48.8,"percent":0.063181,"size":11806354},{"date":"2017-04-05","code":"sz300622","begin":46.15,"high":48.89,"low":42.5,"end":45.9,"percent":0.032621,"size":12821425},{"date":"2017-03-31","code":"sz300622","begin":44.45,"high":44.45,"low":44.45,"end":44.45,"percent":0.099975,"size":212358},{"date":"2017-03-30","code":"sz300622","begin":40.41,"high":40.41,"low":40.41,"end":40.41,"percent":0.099891,"size":196475},{"date":"2017-03-29","code":"sz300622","begin":36.74,"high":36.74,"low":36.74,"end":36.74,"percent":0.1,"size":15095},{"date":"2017-03-28","code":"sz300622","begin":33.4,"high":33.4,"low":33.4,"end":33.4,"percent":0.100132,"size":17000},{"date":"2017-03-27","code":"sz300622","begin":30.36,"high":30.36,"low":30.36,"end":30.36,"percent":0.1,"size":12100},{"date":"2017-03-24","code":"sz300622","begin":27.6,"high":27.6,"low":27.6,"end":27.6,"percent":0.10004,"size":3921},{"date":"2017-03-23","code":"sz300622","begin":25.09,"high":25.09,"low":25.09,"end":25.09,"percent":0.099956,"size":1700},{"date":"2017-03-22","code":"sz300622","begin":22.81,"high":22.81,"low":22.81,"end":22.81,"percent":0.099807,"size":6009},{"date":"2017-03-21","code":"sz300622","begin":20.74,"high":20.74,"low":20.74,"end":20.74,"percent":0.100265,"size":500},{"date":"2017-03-20","code":"sz300622","begin":18.85,"high":18.85,"low":18.85,"end":18.85,"percent":0.099767,"size":6000},{"date":"2017-03-17","code":"sz300622","begin":17.14,"high":17.14,"low":17.14,"end":17.14,"percent":0.100128,"size":1500},{"date":"2017-03-16","code":"sz300622","begin":15.58,"high":15.58,"low":15.58,"end":15.58,"percent":0.100282,"size":1406},{"date":"2017-03-15","code":"sz300622","begin":11.8,"high":14.16,"low":11.8,"end":14.16,"percent":0.440488,"size":5105}]