[{"date":"2017-12-11","code":"sz300620","begin":38.38,"high":38.95,"low":38.29,"end":38.72,"percent":0.005714,"size":851524},{"date":"2017-12-08","code":"sz300620","begin":37.4,"high":39.08,"low":37.08,"end":38.5,"percent":0.031342,"size":1457882},{"date":"2017-12-07","code":"sz300620","begin":36.4,"high":37.83,"low":36.2,"end":37.33,"percent":0.017166,"size":1148063},{"date":"2017-12-06","code":"sz300620","begin":35.32,"high":36.8,"low":35.25,"end":36.7,"percent":0.031189,"size":1097841},{"date":"2017-12-05","code":"sz300620","begin":37,"high":37.68,"low":35,"end":35.59,"percent":-0.047377,"size":1348600},{"date":"2017-12-04","code":"sz300620","begin":39.5,"high":39.67,"low":37.3,"end":37.36,"percent":-0.066467,"size":1645445},{"date":"2017-12-01","code":"sz300620","begin":39.18,"high":40.38,"low":39,"end":40.02,"percent":0.025365,"size":998844},{"date":"2017-11-30","code":"sz300620","begin":38.91,"high":40.33,"low":38.55,"end":39.03,"percent":0.003342,"size":1315835},{"date":"2017-11-29","code":"sz300620","begin":39.5,"high":39.65,"low":37.5,"end":38.9,"percent":-0.008917,"size":1212466},{"date":"2017-11-28","code":"sz300620","begin":38.35,"high":39.49,"low":38.29,"end":39.25,"percent":0.03644,"size":1295884},{"date":"2017-11-27","code":"sz300620","begin":41.47,"high":41.48,"low":37.75,"end":37.87,"percent":-0.089663,"size":1900568},{"date":"2017-11-24","code":"sz300620","begin":41.16,"high":42.7,"low":41.15,"end":41.6,"percent":-0.00716,"size":1592426},{"date":"2017-11-23","code":"sz300620","begin":44.6,"high":45.1,"low":41.9,"end":41.9,"percent":-0.068889,"size":2010326},{"date":"2017-11-22","code":"sz300620","begin":45.24,"high":46.05,"low":43.9,"end":45,"percent":-0.010336,"size":2554700},{"date":"2017-11-21","code":"sz300620","begin":45.56,"high":46.64,"low":42.81,"end":45.47,"percent":0.002204,"size":3171834},{"date":"2017-11-20","code":"sz300620","begin":43.5,"high":45.85,"low":42.57,"end":45.37,"percent":0.019322,"size":2913315},{"date":"2017-11-17","code":"sz300620","begin":48.85,"high":49.56,"low":44.51,"end":44.51,"percent":-0.100081,"size":4015270},{"date":"2017-11-16","code":"sz300620","begin":49.97,"high":51.76,"low":48.15,"end":49.46,"percent":-0.018651,"size":3317441},{"date":"2017-11-15","code":"sz300620","begin":51,"high":52.41,"low":48.7,"end":50.4,"percent":-0.034113,"size":4643026},{"date":"2017-11-14","code":"sz300620","begin":49.99,"high":53.55,"low":49.5,"end":52.18,"percent":0.029597,"size":6513246},{"date":"2017-11-13","code":"sz300620","begin":50,"high":51.38,"low":49.21,"end":50.68,"percent":0.062028,"size":7131718},{"date":"2017-11-10","code":"sz300620","begin":43.3,"high":47.72,"low":43.23,"end":47.72,"percent":0.100046,"size":2964616},{"date":"2017-11-09","code":"sz300620","begin":42.9,"high":43.48,"low":42.5,"end":43.38,"percent":0.004632,"size":1499841},{"date":"2017-11-08","code":"sz300620","begin":43.72,"high":44.56,"low":43.02,"end":43.18,"percent":-0.010314,"size":2314426},{"date":"2017-11-07","code":"sz300620","begin":43.3,"high":43.73,"low":42.5,"end":43.63,"percent":0.006691,"size":1730537},{"date":"2017-11-06","code":"sz300620","begin":43,"high":43.8,"low":42.68,"end":43.34,"percent":0.020245,"size":2297104},{"date":"2017-11-03","code":"sz300620","begin":42.2,"high":43.45,"low":41.56,"end":42.48,"percent":-0.006083,"size":1930465},{"date":"2017-11-02","code":"sz300620","begin":41.85,"high":42.87,"low":41.02,"end":42.74,"percent":0.023222,"size":2596381},{"date":"2017-11-01","code":"sz300620","begin":39.83,"high":42.25,"low":39.71,"end":41.77,"percent":0.046867,"size":1932639},{"date":"2017-10-31","code":"sz300620","begin":39.19,"high":39.9,"low":38.86,"end":39.9,"percent":0.019157,"size":683140},{"date":"2017-10-30","code":"sz300620","begin":40.51,"high":40.78,"low":38,"end":39.15,"percent":-0.044656,"size":1237370},{"date":"2017-10-27","code":"sz300620","begin":41.25,"high":41.7,"low":40.6,"end":40.98,"percent":-0.012292,"size":1047965},{"date":"2017-10-26","code":"sz300620","begin":40.83,"high":41.6,"low":40.51,"end":41.49,"percent":0.016165,"size":1409995},{"date":"2017-10-25","code":"sz300620","begin":39.54,"high":41.1,"low":39.54,"end":40.83,"percent":0.032886,"size":1509726},{"date":"2017-10-24","code":"sz300620","begin":40.01,"high":40.27,"low":39.01,"end":39.53,"percent":-0.011503,"size":948286},{"date":"2017-10-23","code":"sz300620","begin":39.62,"high":40.42,"low":39.62,"end":39.99,"percent":0.00301,"size":853475},{"date":"2017-10-20","code":"sz300620","begin":38.38,"high":39.93,"low":38.31,"end":39.87,"percent":0.030765,"size":1057270},{"date":"2017-10-19","code":"sz300620","begin":38.28,"high":38.93,"low":37.83,"end":38.68,"percent":0.017092,"size":1023360},{"date":"2017-10-18","code":"sz300620","begin":39.69,"high":40.17,"low":37.72,"end":38.03,"percent":-0.042065,"size":1555581},{"date":"2017-10-17","code":"sz300620","begin":39.49,"high":40.15,"low":39.18,"end":39.7,"percent":0.005318,"size":903079},{"date":"2017-10-16","code":"sz300620","begin":42.93,"high":42.93,"low":39.49,"end":39.49,"percent":-0.071915,"size":2397364},{"date":"2017-10-13","code":"sz300620","begin":42.43,"high":43.07,"low":42.03,"end":42.55,"percent":0.006624,"size":1262678},{"date":"2017-10-12","code":"sz300620","begin":41.7,"high":43.2,"low":41.5,"end":42.27,"percent":0.011244,"size":1556163},{"date":"2017-10-11","code":"sz300620","begin":43.75,"high":44.25,"low":41.8,"end":41.8,"percent":-0.04675,"size":2256595},{"date":"2017-10-10","code":"sz300620","begin":43.3,"high":43.93,"low":42.22,"end":43.85,"percent":-0.001594,"size":2444456},{"date":"2017-10-09","code":"sz300620","begin":45.5,"high":46.3,"low":43.55,"end":43.92,"percent":-0.006784,"size":2938083},{"date":"2017-09-29","code":"sz300620","begin":44,"high":45.66,"low":43.9,"end":44.22,"percent":0.011205,"size":2611306},{"date":"2017-09-28","code":"sz300620","begin":43.65,"high":44.99,"low":43.08,"end":43.73,"percent":-0.014202,"size":3061145},{"date":"2017-09-27","code":"sz300620","begin":40.84,"high":45.08,"low":40.84,"end":44.36,"percent":0.082479,"size":3828265},{"date":"2017-09-26","code":"sz300620","begin":43.14,"high":43.33,"low":40.1,"end":40.98,"percent":-0.070116,"size":3085109},{"date":"2017-09-25","code":"sz300620","begin":41.8,"high":46.56,"low":41.62,"end":44.07,"percent":0.041106,"size":3961507},{"date":"2017-09-22","code":"sz300620","begin":40.78,"high":42.62,"low":40.3,"end":42.33,"percent":0.037246,"size":2219971},{"date":"2017-09-21","code":"sz300620","begin":43.59,"high":43.59,"low":40.76,"end":40.81,"percent":-0.060111,"size":2800708},{"date":"2017-09-20","code":"sz300620","begin":42.57,"high":43.48,"low":41.7,"end":43.42,"percent":0.006257,"size":2862650},{"date":"2017-09-19","code":"sz300620","begin":39.89,"high":44.1,"low":39.88,"end":43.15,"percent":0.076328,"size":4404720},{"date":"2017-09-18","code":"sz300620","begin":40,"high":40.23,"low":39,"end":40.09,"percent":-0.005704,"size":1837518},{"date":"2017-09-15","code":"sz300620","begin":39.77,"high":40.61,"low":38.7,"end":40.32,"percent":0.018182,"size":2859700},{"date":"2017-09-14","code":"sz300620","begin":37.9,"high":40.47,"low":37.88,"end":39.6,"percent":0.042105,"size":3289705},{"date":"2017-09-13","code":"sz300620","begin":38.11,"high":38.8,"low":37.48,"end":38,"percent":-0.009643,"size":1429653},{"date":"2017-09-12","code":"sz300620","begin":38.1,"high":39.52,"low":37.88,"end":38.37,"percent":0.004187,"size":2255430},{"date":"2017-09-11","code":"sz300620","begin":37.56,"high":38.48,"low":37.46,"end":38.21,"percent":0.012454,"size":1419555},{"date":"2017-09-08","code":"sz300620","begin":38.11,"high":38.77,"low":37.5,"end":37.74,"percent":-0.014364,"size":2099781},{"date":"2017-09-07","code":"sz300620","begin":39.25,"high":40.98,"low":38.29,"end":38.29,"percent":-0.025204,"size":3281847},{"date":"2017-09-06","code":"sz300620","begin":38.82,"high":39.37,"low":38,"end":39.28,"percent":-0.004309,"size":2611564},{"date":"2017-09-05","code":"sz300620","begin":38.25,"high":41.05,"low":38.25,"end":39.45,"percent":0.043099,"size":3673589},{"date":"2017-09-04","code":"sz300620","begin":37.5,"high":38.77,"low":37,"end":37.82,"percent":0.007459,"size":2572347},{"date":"2017-09-01","code":"sz300620","begin":37.99,"high":38.56,"low":37.17,"end":37.54,"percent":-0.012885,"size":2701775},{"date":"2017-08-31","code":"sz300620","begin":36.53,"high":38.38,"low":36.52,"end":38.03,"percent":0.038787,"size":3119095},{"date":"2017-08-30","code":"sz300620","begin":37.17,"high":37.2,"low":36.19,"end":36.61,"percent":-0.01955,"size":2477400},{"date":"2017-08-29","code":"sz300620","begin":38.09,"high":38.47,"low":37.28,"end":37.34,"percent":-0.019175,"size":3858149},{"date":"2017-08-28","code":"sz300620","begin":36.8,"high":39.15,"low":36.43,"end":38.07,"percent":0.052239,"size":5412537},{"date":"2017-08-25","code":"sz300620","begin":32.82,"high":36.18,"low":32.79,"end":36.18,"percent":0.10003,"size":3577137},{"date":"2017-08-24","code":"sz300620","begin":32.61,"high":33.88,"low":32.6,"end":32.89,"percent":0.003356,"size":1651659},{"date":"2017-08-23","code":"sz300620","begin":32.63,"high":33.18,"low":32.18,"end":32.78,"percent":0.004597,"size":851585},{"date":"2017-08-22","code":"sz300620","begin":32.96,"high":33.59,"low":32.5,"end":32.63,"percent":-0.012708,"size":1351410},{"date":"2017-08-21","code":"sz300620","begin":32.19,"high":33.22,"low":32.19,"end":33.05,"percent":0.027355,"size":1033734},{"date":"2017-08-18","code":"sz300620","begin":32.44,"high":32.44,"low":32.08,"end":32.17,"percent":-0.012281,"size":733342},{"date":"2017-08-17","code":"sz300620","begin":32.53,"high":33.1,"low":32.15,"end":32.57,"percent":0.00123,"size":1143865},{"date":"2017-08-16","code":"sz300620","begin":31.71,"high":32.95,"low":31.7,"end":32.53,"percent":0.025213,"size":1386653},{"date":"2017-08-15","code":"sz300620","begin":31.5,"high":31.96,"low":31.44,"end":31.73,"percent":0.007302,"size":566142},{"date":"2017-08-14","code":"sz300620","begin":30.76,"high":31.68,"low":30.66,"end":31.5,"percent":0.022727,"size":583059},{"date":"2017-08-11","code":"sz300620","begin":30.78,"high":31.12,"low":30.5,"end":30.8,"percent":-0.020356,"size":707296},{"date":"2017-08-10","code":"sz300620","begin":32.11,"high":32.27,"low":31.27,"end":31.44,"percent":-0.020866,"size":453254},{"date":"2017-08-09","code":"sz300620","begin":31.99,"high":32.29,"low":31.75,"end":32.11,"percent":0.004693,"size":577142},{"date":"2017-08-08","code":"sz300620","begin":31.95,"high":32.06,"low":31.52,"end":31.96,"percent":0.001881,"size":474365},{"date":"2017-08-07","code":"sz300620","begin":31.61,"high":32.02,"low":31.61,"end":31.9,"percent":0.011414,"size":442712},{"date":"2017-08-04","code":"sz300620","begin":31.4,"high":31.62,"low":31,"end":31.54,"percent":0.004139,"size":629739},{"date":"2017-08-03","code":"sz300620","begin":31.08,"high":31.98,"low":30.98,"end":31.41,"percent":0.011269,"size":567580},{"date":"2017-08-02","code":"sz300620","begin":32,"high":32,"low":31.06,"end":31.06,"percent":-0.026027,"size":590828},{"date":"2017-08-01","code":"sz300620","begin":31.88,"high":32.13,"low":31.6,"end":31.89,"percent":-0.000313,"size":516700},{"date":"2017-07-31","code":"sz300620","begin":32.06,"high":32.58,"low":31.7,"end":31.9,"percent":-0.004059,"size":529402},{"date":"2017-07-28","code":"sz300620","begin":32.6,"high":33.15,"low":32,"end":32.03,"percent":-0.01989,"size":781555},{"date":"2017-07-27","code":"sz300620","begin":31.72,"high":32.92,"low":31.4,"end":32.68,"percent":0.030265,"size":1011100},{"date":"2017-07-26","code":"sz300620","begin":32,"high":32.07,"low":31.63,"end":31.72,"percent":-0.003143,"size":373342},{"date":"2017-07-25","code":"sz300620","begin":31.95,"high":32.16,"low":31.55,"end":31.82,"percent":-0.005314,"size":444066},{"date":"2017-07-24","code":"sz300620","begin":31.51,"high":32.3,"low":31,"end":31.99,"percent":0.000313,"size":844315},{"date":"2017-07-21","code":"sz300620","begin":32.54,"high":32.54,"low":31.64,"end":31.98,"percent":0.001252,"size":549006},{"date":"2017-07-20","code":"sz300620","begin":31.91,"high":32.65,"low":31.8,"end":31.94,"percent":0.00094,"size":932425},{"date":"2017-07-19","code":"sz300620","begin":31.71,"high":32.19,"low":30.94,"end":31.91,"percent":-0.000939,"size":875858},{"date":"2017-07-18","code":"sz300620","begin":32.35,"high":32.6,"low":30.53,"end":31.94,"percent":-0.016323,"size":1214885},{"date":"2017-07-17","code":"sz300620","begin":35.2,"high":35.3,"low":32.47,"end":32.47,"percent":-0.100055,"size":1576496},{"date":"2017-07-14","code":"sz300620","begin":35.69,"high":36.79,"low":35.65,"end":36.08,"percent":0.006135,"size":853508},{"date":"2017-07-13","code":"sz300620","begin":36.04,"high":36.33,"low":35.57,"end":35.86,"percent":-0.014835,"size":633823},{"date":"2017-07-12","code":"sz300620","begin":35.99,"high":36.5,"low":34.5,"end":36.4,"percent":0.017328,"size":978626},{"date":"2017-07-11","code":"sz300620","begin":36.25,"high":36.79,"low":35.75,"end":35.78,"percent":-0.014597,"size":934200},{"date":"2017-07-10","code":"sz300620","begin":37.9,"high":38,"low":36,"end":36.31,"percent":-0.051711,"size":1859700},{"date":"2017-07-07","code":"sz300620","begin":36.99,"high":38.5,"low":36.8,"end":38.29,"percent":0.037107,"size":2168491},{"date":"2017-07-06","code":"sz300620","begin":36.28,"high":36.98,"low":35.96,"end":36.92,"percent":0.012339,"size":1522519},{"date":"2017-07-05","code":"sz300620","begin":35.38,"high":36.68,"low":35.32,"end":36.47,"percent":0.026168,"size":1258783},{"date":"2017-07-04","code":"sz300620","begin":35.7,"high":35.95,"low":35.32,"end":35.54,"percent":-0.004482,"size":735956},{"date":"2017-07-03","code":"sz300620","begin":34.77,"high":35.8,"low":34.47,"end":35.7,"percent":0.032389,"size":1115982},{"date":"2017-06-30","code":"sz300620","begin":34.05,"high":34.85,"low":33.84,"end":34.58,"percent":0.013482,"size":662858},{"date":"2017-06-29","code":"sz300620","begin":33.72,"high":34.51,"low":33.72,"end":34.12,"percent":0.009766,"size":465223},{"date":"2017-06-28","code":"sz300620","begin":34.76,"high":34.76,"low":33.69,"end":33.79,"percent":-0.029023,"size":680556},{"date":"2017-06-27","code":"sz300620","begin":34.58,"high":35.22,"low":34.58,"end":34.8,"percent":0.002016,"size":524252},{"date":"2017-06-26","code":"sz300620","begin":34.3,"high":34.78,"low":33.81,"end":34.73,"percent":0.011652,"size":537314},{"date":"2017-06-23","code":"sz300620","begin":34.6,"high":34.87,"low":33.28,"end":34.33,"percent":-0.00809,"size":1056900},{"date":"2017-06-22","code":"sz300620","begin":35.9,"high":36.23,"low":34.61,"end":34.61,"percent":-0.0426,"size":958614},{"date":"2017-06-21","code":"sz300620","begin":36.36,"high":36.36,"low":35.56,"end":36.15,"percent":0.000831,"size":884900},{"date":"2017-06-20","code":"sz300620","begin":37.07,"high":37.12,"low":36.08,"end":36.12,"percent":-0.015804,"size":1017081},{"date":"2017-06-19","code":"sz300620","begin":36.3,"high":36.74,"low":35.9,"end":36.7,"percent":0.010741,"size":991523},{"date":"2017-06-16","code":"sz300620","begin":36.57,"high":36.57,"low":35.81,"end":36.31,"percent":-0.003841,"size":1216241},{"date":"2017-06-15","code":"sz300620","begin":34.94,"high":36.85,"low":34.84,"end":36.45,"percent":0.046512,"size":1865479},{"date":"2017-06-14","code":"sz300620","begin":35.11,"high":35.3,"low":34.56,"end":34.83,"percent":-0.008257,"size":802706},{"date":"2017-06-13","code":"sz300620","begin":33.55,"high":35.27,"low":33.55,"end":35.12,"percent":0.036294,"size":909776},{"date":"2017-06-12","code":"sz300620","begin":35.42,"high":35.43,"low":33.8,"end":33.89,"percent":-0.054145,"size":1159942},{"date":"2017-06-09","code":"sz300620","begin":34.87,"high":35.83,"low":34.65,"end":35.83,"percent":0.025766,"size":1076279},{"date":"2017-06-08","code":"sz300620","begin":35.4,"high":35.66,"low":34.81,"end":34.93,"percent":-0.01661,"size":943600},{"date":"2017-06-07","code":"sz300620","begin":33.96,"high":35.84,"low":33.89,"end":35.52,"percent":0.045936,"size":1440887},{"date":"2017-06-06","code":"sz300620","begin":33.5,"high":34.19,"low":33.36,"end":33.96,"percent":0.001179,"size":514067},{"date":"2017-06-05","code":"sz300620","begin":33.6,"high":34.5,"low":33.6,"end":33.92,"percent":0.009223,"size":804261},{"date":"2017-06-02","code":"sz300620","begin":32.5,"high":33.98,"low":32,"end":33.61,"percent":0.034154,"size":774520},{"date":"2017-06-01","code":"sz300620","begin":34.31,"high":34.5,"low":32.5,"end":32.5,"percent":-0.06367,"size":1111037},{"date":"2017-05-31","code":"sz300620","begin":35.99,"high":36.58,"low":34.68,"end":34.71,"percent":-0.000576,"size":1379829},{"date":"2017-05-26","code":"sz300620","begin":34.64,"high":35.27,"low":34.16,"end":34.73,"percent":0.006959,"size":896073},{"date":"2017-05-25","code":"sz300620","begin":34.35,"high":34.68,"low":33.18,"end":34.49,"percent":0.003491,"size":1066137},{"date":"2017-05-24","code":"sz300620","begin":33.8,"high":34.62,"low":33.41,"end":34.37,"percent":0.018672,"size":886113},{"date":"2017-05-23","code":"sz300620","begin":35.17,"high":35.47,"low":33.66,"end":33.74,"percent":-0.040114,"size":1121537},{"date":"2017-05-22","code":"sz300620","begin":37.96,"high":38.54,"low":34.81,"end":35.15,"percent":-0.080324,"size":1514727},{"date":"2017-05-19","code":"sz300620","begin":39.12,"high":39.46,"low":38.05,"end":38.22,"percent":-0.022006,"size":1062528},{"date":"2017-05-18","code":"sz300620","begin":38.2,"high":39.6,"low":38.02,"end":39.08,"percent":0.012698,"size":1653299},{"date":"2017-05-17","code":"sz300620","begin":38.43,"high":39.79,"low":38.41,"end":38.59,"percent":0.002859,"size":1703157},{"date":"2017-05-16","code":"sz300620","begin":37.14,"high":38.55,"low":36.42,"end":38.48,"percent":0.029428,"size":1466307},{"date":"2017-05-15","code":"sz300620","begin":37.94,"high":37.95,"low":37.29,"end":37.38,"percent":-0.005587,"size":945335},{"date":"2017-05-12","code":"sz300620","begin":37.15,"high":37.97,"low":36.88,"end":37.59,"percent":0.012389,"size":1392433},{"date":"2017-05-11","code":"sz300620","begin":36,"high":37.29,"low":35.33,"end":37.13,"percent":0.01089,"size":1655172},{"date":"2017-05-10","code":"sz300620","begin":37.9,"high":38.88,"low":36.7,"end":36.73,"percent":-0.035452,"size":1568784},{"date":"2017-05-09","code":"sz300620","begin":37.49,"high":38.22,"low":36.86,"end":38.08,"percent":0.014655,"size":1603201},{"date":"2017-05-08","code":"sz300620","begin":39.08,"high":39.28,"low":37.51,"end":37.53,"percent":-0.049392,"size":1276611},{"date":"2017-05-05","code":"sz300620","begin":40.88,"high":41.29,"low":39.48,"end":39.48,"percent":-0.037777,"size":1376144},{"date":"2017-05-04","code":"sz300620","begin":41.82,"high":42.18,"low":41,"end":41.03,"percent":-0.029106,"size":1213419},{"date":"2017-05-03","code":"sz300620","begin":42.38,"high":42.92,"low":41.1,"end":42.26,"percent":-0.002596,"size":1815178},{"date":"2017-05-02","code":"sz300620","begin":42.57,"high":42.99,"low":42.25,"end":42.37,"percent":-0.007031,"size":1052570},{"date":"2017-04-28","code":"sz300620","begin":42.8,"high":43,"low":42.41,"end":42.67,"percent":-0.009057,"size":1483336},{"date":"2017-04-27","code":"sz300620","begin":40.55,"high":43.2,"low":40.4,"end":43.06,"percent":0.055651,"size":2812219},{"date":"2017-04-26","code":"sz300620","begin":40,"high":41.88,"low":39.71,"end":40.79,"percent":0.013416,"size":1795296},{"date":"2017-04-25","code":"sz300620","begin":39.15,"high":40.54,"low":39.15,"end":40.25,"percent":0.028885,"size":1379878},{"date":"2017-04-24","code":"sz300620","begin":41.2,"high":41.2,"low":39.05,"end":39.12,"percent":-0.052785,"size":1431123},{"date":"2017-04-21","code":"sz300620","begin":41.1,"high":41.79,"low":41,"end":41.3,"percent":0.009533,"size":1108140},{"date":"2017-04-20","code":"sz300620","begin":41.9,"high":42.27,"low":40.11,"end":40.91,"percent":-0.030569,"size":1414428},{"date":"2017-04-19","code":"sz300620","begin":40.75,"high":42.41,"low":40.31,"end":42.2,"percent":0.024023,"size":1696055},{"date":"2017-04-18","code":"sz300620","begin":41.95,"high":42.19,"low":41.21,"end":41.21,"percent":-0.011039,"size":1156856},{"date":"2017-04-17","code":"sz300620","begin":42.55,"high":43.4,"low":41.67,"end":41.67,"percent":-0.1,"size":2763018},{"date":"2017-04-14","code":"sz300620","begin":46.85,"high":46.95,"low":46.01,"end":46.3,"percent":-0.026288,"size":1480319},{"date":"2017-04-13","code":"sz300620","begin":47.4,"high":48.3,"low":47.12,"end":47.55,"percent":0.006562,"size":1434633},{"date":"2017-04-12","code":"sz300620","begin":48.2,"high":48.46,"low":47.1,"end":47.24,"percent":-0.02073,"size":2003939},{"date":"2017-04-11","code":"sz300620","begin":47.48,"high":48.44,"low":46.7,"end":48.24,"percent":0.02682,"size":2874397},{"date":"2017-04-10","code":"sz300620","begin":51,"high":51.19,"low":46.97,"end":46.98,"percent":-0.098619,"size":4616628},{"date":"2017-04-07","code":"sz300620","begin":54.01,"high":55.68,"low":52.1,"end":52.12,"percent":-0.047166,"size":3767045},{"date":"2017-04-06","code":"sz300620","begin":53.4,"high":57.3,"low":53.12,"end":54.7,"percent":0.022048,"size":5159875},{"date":"2017-04-05","code":"sz300620","begin":52,"high":54.94,"low":50.69,"end":53.52,"percent":-0.048872,"size":5674095},{"date":"2017-03-31","code":"sz300620","begin":61.01,"high":62,"low":56.27,"end":56.27,"percent":-0.099968,"size":8936270},{"date":"2017-03-30","code":"sz300620","begin":62.52,"high":62.52,"low":59,"end":62.52,"percent":0.09993,"size":13572757},{"date":"2017-03-29","code":"sz300620","begin":56.84,"high":56.84,"low":56.84,"end":56.84,"percent":0.100058,"size":72156},{"date":"2017-03-28","code":"sz300620","begin":51.67,"high":51.67,"low":51.67,"end":51.67,"percent":0.100064,"size":43186},{"date":"2017-03-27","code":"sz300620","begin":46.97,"high":46.97,"low":46.97,"end":46.97,"percent":0.1,"size":17428},{"date":"2017-03-24","code":"sz300620","begin":42.7,"high":42.7,"low":42.7,"end":42.7,"percent":0.099948,"size":24007},{"date":"2017-03-23","code":"sz300620","begin":38.82,"high":38.82,"low":38.82,"end":38.82,"percent":0.100028,"size":4242},{"date":"2017-03-22","code":"sz300620","begin":35.29,"high":35.29,"low":35.29,"end":35.29,"percent":0.100062,"size":4952},{"date":"2017-03-21","code":"sz300620","begin":32.08,"high":32.08,"low":32.08,"end":32.08,"percent":0.100137,"size":5007},{"date":"2017-03-20","code":"sz300620","begin":29.16,"high":29.16,"low":29.16,"end":29.16,"percent":0.099962,"size":1200},{"date":"2017-03-17","code":"sz300620","begin":26.51,"high":26.51,"low":26.51,"end":26.51,"percent":0.1,"size":2500},{"date":"2017-03-16","code":"sz300620","begin":24.1,"high":24.1,"low":24.1,"end":24.1,"percent":0.099954,"size":2000},{"date":"2017-03-15","code":"sz300620","begin":21.91,"high":21.91,"low":21.91,"end":21.91,"percent":0.0999,"size":800},{"date":"2017-03-14","code":"sz300620","begin":19.92,"high":19.92,"low":19.92,"end":19.92,"percent":0.099945,"size":1000},{"date":"2017-03-13","code":"sz300620","begin":18.11,"high":18.11,"low":18.11,"end":18.11,"percent":0.100243,"size":1200},{"date":"2017-03-10","code":"sz300620","begin":14.95,"high":16.46,"low":14.95,"end":16.46,"percent":0.44007,"size":2300}]